Metadata-Version: 2.1
Name: appdynamics-proxysupport-linux-x64
Version: 11.80.22
Summary: Proxysupport for AppDynamics Python agent
Home-page: http://www.appdynamics.com
Author: AppDynamics
Author-email: support@appdynamics.com
License: Proprietary
